odoo/addons/utm_source_multi_company/README.rst
odoo/addons/utm_source_multi_company/__init__.py
odoo/addons/utm_source_multi_company/__manifest__.py
odoo/addons/utm_source_multi_company/i18n/it.po
odoo/addons/utm_source_multi_company/i18n/utm_source_multi_company.pot
odoo/addons/utm_source_multi_company/models/__init__.py
odoo/addons/utm_source_multi_company/models/utm_source.py
odoo/addons/utm_source_multi_company/readme/CONTRIBUTORS.md
odoo/addons/utm_source_multi_company/readme/DESCRIPTION.md
odoo/addons/utm_source_multi_company/security/utm_source.xml
odoo/addons/utm_source_multi_company/static/description/icon.png
odoo/addons/utm_source_multi_company/static/description/index.html
odoo/addons/utm_source_multi_company/views/utm_source.xml
odoo_addon_utm_source_multi_company-18.0.1.0.0.4.dist-info/METADATA
odoo_addon_utm_source_multi_company-18.0.1.0.0.4.dist-info/WHEEL
odoo_addon_utm_source_multi_company-18.0.1.0.0.4.dist-info/top_level.txt
odoo_addon_utm_source_multi_company-18.0.1.0.0.4.dist-info/RECORD
